odoo/addons/account_bank_statement_import_online_ponto/README.rst
odoo/addons/account_bank_statement_import_online_ponto/__init__.py
odoo/addons/account_bank_statement_import_online_ponto/__manifest__.py
odoo/addons/account_bank_statement_import_online_ponto/data/ir_cron.xml
odoo/addons/account_bank_statement_import_online_ponto/i18n/account_bank_statement_import_online_ponto.pot
odoo/addons/account_bank_statement_import_online_ponto/i18n/fr_FR.po
odoo/addons/account_bank_statement_import_online_ponto/models/__init__.py
odoo/addons/account_bank_statement_import_online_ponto/models/online_bank_statement_provider_ponto.py
odoo/addons/account_bank_statement_import_online_ponto/models/ponto_buffer.py
odoo/addons/account_bank_statement_import_online_ponto/models/ponto_buffer_line.py
odoo/addons/account_bank_statement_import_online_ponto/models/ponto_interface.py
odoo/addons/account_bank_statement_import_online_ponto/readme/CONFIGURE.rst
odoo/addons/account_bank_statement_import_online_ponto/readme/CONTRIBUTORS.rst
odoo/addons/account_bank_statement_import_online_ponto/readme/DESCRIPTION.rst
odoo/addons/account_bank_statement_import_online_ponto/readme/USAGE.rst
odoo/addons/account_bank_statement_import_online_ponto/security/ir.model.access.csv
odoo/addons/account_bank_statement_import_online_ponto/static/description/icon.png
odoo/addons/account_bank_statement_import_online_ponto/static/description/index.html
odoo/addons/account_bank_statement_import_online_ponto/tests/__init__.py
odoo/addons/account_bank_statement_import_online_ponto/tests/test_account_statement_import_online_ponto.py
odoo/addons/account_bank_statement_import_online_ponto/tests/test_ponto_interface.py
odoo/addons/account_bank_statement_import_online_ponto/views/ir_actions_act_window.xml
odoo/addons/account_bank_statement_import_online_ponto/views/ir_ui_menu.xml
odoo/addons/account_bank_statement_import_online_ponto/views/online_bank_statement_provider.xml
odoo12_addon_account_bank_statement_import_online_ponto-12.0.1.3.0.dist-info/METADATA
odoo12_addon_account_bank_statement_import_online_ponto-12.0.1.3.0.dist-info/WHEEL
odoo12_addon_account_bank_statement_import_online_ponto-12.0.1.3.0.dist-info/top_level.txt
odoo12_addon_account_bank_statement_import_online_ponto-12.0.1.3.0.dist-info/RECORD
